AUTHORS.rst
CONTRIBUTING.rst
HISTORY.rst
LICENSE
MANIFEST.in
README.rst
setup.cfg
setup.py
django_telegram_bots.egg-info/PKG-INFO
django_telegram_bots.egg-info/SOURCES.txt
django_telegram_bots.egg-info/dependency_links.txt
django_telegram_bots.egg-info/not-zip-safe
django_telegram_bots.egg-info/requires.txt
django_telegram_bots.egg-info/top_level.txt
telegram_bots/__init__.py
telegram_bots/admin.py
telegram_bots/api_urls.py
telegram_bots/apps.py
telegram_bots/forms.py
telegram_bots/models.py
telegram_bots/permissions.py
telegram_bots/serializers.py
telegram_bots/services.py
telegram_bots/signals.py
telegram_bots/urls.py
telegram_bots/utils.py
telegram_bots/validators.py
telegram_bots/views.py
telegram_bots/viewsets.py
telegram_bots/migrations/0001_initial.py
telegram_bots/migrations/0002_auto_20180427_1318.py
telegram_bots/migrations/__init__.py
telegram_bots/static/css/telegram_bots.css
telegram_bots/static/js/telegram_bots.js
telegram_bots/templates/telegram_bots/base.html
telegram_bots/templates/telegram_bots/bot_confirm_delete.html
telegram_bots/templates/telegram_bots/bot_detail.html
telegram_bots/templates/telegram_bots/bot_list.html
telegram_bots/templates/telegram_bots/button.html
telegram_bots/templatetags/__init__.py
telegram_bots/templatetags/telegram_bots_tags.py