Metadata-Version: 1.1
Name: django-telegram-bots
Version: 0.1.12
Summary: App for creating telegram bots, with setting webhook, receive messages and subscribe users
Home-page: https://github.com/narnikgamarnikus/django-telegram-bots
Author: Vladimir Myshkovski
Author-email: vladimirmyshkovski@gmail.com
License: MIT
Keywords: django-telegram-bots
Platform: UNKNOWN
Classifier: Development Status :: 3 - Alpha
Classifier: Framework :: Django
Classifier: Framework :: Django :: 1.10
Classifier: Intended Audience :: Developers
Classifier: License :: OSI Approved :: BSD License
Classifier: Natural Language :: English
Classifier: Programming Language :: Python :: 3
Classifier: Programming Language :: Python :: 3.4
Classifier: Programming Language :: Python :: 3.5
